condor_git_config.py
condor_git_config-0.1.5.dist-info/entry_points.txt
condor_git_config-0.1.5.dist-info/WHEEL
condor_git_config-0.1.5.dist-info/METADATA
condor_git_config-0.1.5.dist-info/RECORD
