Metadata-Version: 2.1
Name: condor_git_config
Version: 0.1.5
Summary: dynamically configure an HTCondor node from a git repository
Keywords: htcondor,condor,configuration
Author-email: Max Fischer <maxfischer2781@gmail.com>
Requires-Python: >=3.6
Classifier: Intended Audience :: Developers
Classifier: Intended Audience :: System Administrators
Classifier: License :: OSI Approved :: MIT License
Classifier: Programming Language :: Python :: 3 :: Only
Requires-Dist: filelock
Requires-Dist: pytest ; extra == "test"
Requires-Dist: flake8 ; extra == "test"
Requires-Dist: flake8-bugbear ; extra == "test"
Requires-Dist: black ; extra == "test" and ( implementation_name=='cpython')
Requires-Dist: mypy ; extra == "test" and ( implementation_name=='cpython')
Requires-Dist: types-filelock ; extra == "test" and ( implementation_name=='cpython')
Project-URL: Source, https://github.com/matterminers/condor-git-config
Provides-Extra: test
